metaevobox
